druwez/__init__.py
druwez/_meta.py
druwez/about.py
druwez/clipboard.py
druwez/converterdlg.py
druwez/convertersettings.py
druwez/dialogs.py
druwez/entrytools.py
druwez/errordlg.py
druwez/errors.py
druwez/gtkutils.py
druwez/guistate.py
druwez/i18n.py
druwez/jobdlg.py
druwez/joblist.py
druwez/jsonobj.py
druwez/license.py
druwez/main.py
druwez/mainwin.py
druwez/objects.py
druwez/patterndlg.py
druwez/prefbuttons.py
druwez/preferences.py
druwez/printing.py
druwez/settings.py
druwez/statusbar.py
druwez/tvtools.py
druwez/utils.py
druwez/xdgdirs.py
druwez-0.1.data/data/share/druwez/converters-default.json
druwez-0.1.data/data/share/druwez/ui/contenterror.ui
druwez-0.1.data/data/share/druwez/ui/converterdlg.ui
druwez-0.1.data/data/share/druwez/ui/convertererror.ui
druwez-0.1.data/data/share/druwez/ui/converters.ui
druwez-0.1.data/data/share/druwez/ui/fileerrordlg.ui
druwez-0.1.data/data/share/druwez/ui/job.ui
druwez-0.1.data/data/share/druwez/ui/main.ui
druwez-0.1.data/data/share/druwez/ui/pattern.ui
druwez-0.1.data/data/share/druwez/ui/preferences.ui
usr/share/man/man1/druwez.1
druwez-0.1.dist-info/COPYING
druwez-0.1.dist-info/METADATA
druwez-0.1.dist-info/WHEEL
druwez-0.1.dist-info/entry_points.txt
druwez-0.1.dist-info/top_level.txt
druwez-0.1.dist-info/RECORD
