Metadata-Version: 2.1
Name: druwez
Version: 0.1
Summary: Use drag&drop or copy&paste from file managers to print files
Home-page: https://www.florian-diesch.de/software/druwez/
Author: Florian Diesch
Author-email: devel@florian-diesch.de
Maintainer: Florian Diesch
Maintainer-email: devel@florian-diesch.de
License: GPL-3
Download-URL: https://www.florian-diesch.de/software/druwez/
Platform: UNKNOWN
Requires-Python: >=3.6
